{
    "id": "economy",
    "loadThresholds": {
      "requestsInFlight": {
        "average": "300",
        "gradient": "0",
        "secondDerivative": "0",
        "scaleDownMarginOfGradient": "1.0",
        "scaleDownMarginOfSecondDerivative": "0.2"
      },
      "memoryConsumption": {
        "average": "6000",
        "gradient": "0",
        "secondDerivative": "0",
        "scaleDownMarginOfGradient": "1.0",
        "scaleDownMarginOfSecondDerivative": "0.2"
      },
      "loadAverage": {
        "average": "6000",
        "gradient": "0",
        "secondDerivative": "0",
        "scaleDownMarginOfGradient": "1.0",
        "scaleDownMarginOfSecondDerivative": "0.2"
      }
    }  
}
